LICENSE
MANIFEST.in
README.md
requirements.txt
setup.py
attachi/__init__.py
attachi/attachi.py
attachi.egg-info/PKG-INFO
attachi.egg-info/SOURCES.txt
attachi.egg-info/dependency_links.txt
attachi.egg-info/requires.txt
attachi.egg-info/top_level.txt
scripts/attachi