Metadata-Version: 1.0
Name: attachi
Version: 0.1.2
Summary: Small attachment helper script for openBIS registration.
Home-page: UNKNOWN
Author: Andreas Friedrich
Author-email: andreas.friedrich@uni-tuebingen.de
License: MIT License
